Missing_Values_101703525/Missing_Values_101703525.py
Missing_Values_101703525/__init__.py
Missing_Values_101703525-0.9.dist-info/METADATA
Missing_Values_101703525-0.9.dist-info/WHEEL
Missing_Values_101703525-0.9.dist-info/entry_points.txt
Missing_Values_101703525-0.9.dist-info/top_level.txt
Missing_Values_101703525-0.9.dist-info/RECORD
